skr_cputils/TraverseNestedList.py
skr_cputils/__init__.py
skr_cputils-0.2.dist-info/METADATA
skr_cputils-0.2.dist-info/WHEEL
skr_cputils-0.2.dist-info/entry_points.txt
skr_cputils-0.2.dist-info/top_level.txt
skr_cputils-0.2.dist-info/RECORD
